{"itemData": {"url_name": "30179-satono-diamond", "support_id": 30179, "char_id": 1067, "char_name": "Satono Diamond", "name_jp": "\u30b5\u30c8\u30ce\u30c0\u30a4\u30e4\u30e2\u30f3\u30c9", "name_ko": "\uc0ac\ud1a0\ub178 \ub2e4\uc774\uc544\ubaac\ub4dc", "name_tw": "\u91cc\u898b\u5149\u947d", "rarity": 3, "type": "intelligence", "obtained": "gacha", "release": "2023-12-28", "release_ko": "2025-04-17", "release_zh_tw": "2025-05-01", "effects": [[1, 10, -1, -1, -1, -1, 15, 15, -1, -1, 20, -1], [2, -1, -1, -1, -1, -1, -1, -1, 20, 40, -1, -1], [7, -1, -1, -1, -1, -1, -1, -1, -1, -1, 1, 2], [8, -1, -1, 1, -1, -1, 5, 5, -1, -1, 10, -1], [9, -1, -1, -1, 10, -1, 15, 15, -1, -1, 20, -1], [14, 10, -1, -1, -1, -1, -1, 25, -1, -1, -1, 30], [15, -1, -1, -1, 1, -1, 1, 1, -1, -1, 5, -1], [16, -1, -1, -1, 1, -1, 5, 5, -1, -1, 10, -1], [17, 1, -1, -1, -1, -1, -1, 2, -1, -1, -1, 3], [18, 5, -1, -1, -1, -1, -1, 40, -1, -1, -1, 50], [19, -1, -1, 5, -1, -1, 35, 35, -1, -1, 50, -1], [31, 1, -1, -1, -1, -1, -1, 3, -1, -1, -1, 5]], "hints": {"hint_skills": [202092, 201392, 202152, 202612, 202622, 200342, 200602, 200452], "hint_others": [{"hint_type": 5, "hint_value": 6}, {"hint_type": 30, "hint_value": 5}]}, "event_skills": [202662, 202151, 202091, 200851], "unique": {"level": 30, "effects": [{"type": 101, "value": 80, "value_1": 1, "value_2": 10, "value_3": 30, "value_4": 1}]}}, "eventData": {"ja": "{\"random\":[{\"n\":\"\u65b0\u3057\u3044\u3082\u306e\u3001\u5927\u597d\u304d\u3067\u3059\uff01\",\"c\":[{\"o\":\"\u30c6\u30a3\u30fc\u30ab\u30c3\u30d7\u3067\u98f2\u3080\u306e\u304b\uff1f\",\"r\":[{\"t\":\"gu\",\"v\":\"+10\"},{\"t\":\"bo\",\"v\":\"+5\",\"d\":1067}]},{\"o\":\"\u30e1\u30ed\u30f3\u30bd\u30fc\u30c0\u306f\u521d\u3081\u3066\uff1f\",\"r\":[{\"t\":\"en\",\"v\":\"-10\"},{\"t\":\"st\",\"v\":\"+20\"},{\"t\":\"bo\",\"v\":\"+5\",\"d\":1067}]}]},{\"n\":\"\u96e3\u3057\u3044\u3053\u3068\u3001\u5927\u597d\u304d\u3067\u3059\uff01\",\"c\":[{\"o\":\"\u3088\u3057\u3001\u3084\u3063\u3066\u307f\u3088\u3046\uff01\",\"r\":[{\"t\":\"st\",\"v\":\"+5\"},{\"t\":\"gu\",\"v\":\"+10\"},{\"t\":\"bo\",\"v\":\"+5\",\"d\":1067}]},{\"o\":\"\u307e\u305a\u306f1\u5ea6\u69d8\u5b50\u3092\u898b\u3088\u3046\",\"r\":[{\"t\":\"sk\",\"v\":\"+1\",\"d\":200851},{\"t\":\"bo\",\"v\":\"+5\",\"d\":1067}]}]}],\"arrows\":[{\"n\":\"\u30a2\u30a4\u30aa\u30e9\u30a4\u30c8\u306e\u7cbe\u795e\",\"c\":[{\"o\":\"\u9078\u629e\u80a2\u7121\u3057\",\"r\":[{\"t\":\"mo\",\"v\":\"+1\"},{\"t\":\"in\",\"v\":\"+20\"},{\"t\":\"bo\",\"v\":\"+15\",\"d\":1067},{\"t\":\"di\"},{\"t\":\"mo\",\"v\":\"+1\"},{\"t\":\"in\",\"v\":\"+5\"},{\"t\":\"bo\",\"v\":\"+5\",\"d\":1067}]}]},{\"n\":\"\u30b7\u30ea\u30de\u30ca\u30a4\u30c8\u306e\u6e1a\",\"c\":[{\"o\":\"\u9078\u629e\u80a2\u7121\u3057\",\"r\":[{\"t\":\"en\",\"v\":\"+10\"},{\"t\":\"sp\",\"v\":\"+10\"},{\"t\":\"pt\",\"v\":\"+10\"},{\"t\":\"sk\",\"v\":\"+2\",\"d\":202662},{\"t\":\"bo\",\"v\":\"+5\",\"d\":1067}]}]},{\"n\":\"\u30ab\u30eb\u30bb\u30c9\u30cb\u30fc\u304c\u8f1d\u304f\",\"c\":[{\"o\":\"\u59a5\u5354\u3057\u306a\u3044\u5fc3\u304c\u97ff\u3044\u305f\u304b\u306a\uff1f\",\"r\":[{\"t\":\"in\",\"v\":\"+30\"},{\"t\":\"sk\",\"v\":\"+2\",\"d\":202151},{\"t\":\"bo\",\"v\":\"+5\",\"d\":1067}]},{\"o\":\"\u307f\u3093\u306a\u3001\u3044\u3044\u9854\u3092\u3057\u3066\u3044\u308b\u306a\",\"r\":[{\"t\":\"sp\",\"v\":\"+10\"},{\"t\":\"in\",\"v\":\"+10\"},{\"t\":\"pt\",\"v\":\"+10\"},{\"t\":\"sk\",\"v\":\"+2\",\"d\":202091},{\"t\":\"bo\",\"v\":\"+5\",\"d\":1067}]}]}]}", "ko": "{\"random\":[{\"n\":\"\uc0c8\ub85c\uc6b4 \uac70, \uc815\ub9d0 \uc88b\uc544\ud574\uc694!\",\"c\":[{\"o\":\"\u30c6\u30a3\u30fc\u30ab\u30c3\u30d7\u3067\u98f2\u3080\u306e\u304b\uff1f\",\"r\":[{\"t\":\"gu\",\"v\":\"+10\"},{\"t\":\"bo\",\"v\":\"+5\",\"d\":1067}]},{\"o\":\"\u30e1\u30ed\u30f3\u30bd\u30fc\u30c0\u306f\u521d\u3081\u3066\uff1f\",\"r\":[{\"t\":\"en\",\"v\":\"-10\"},{\"t\":\"st\",\"v\":\"+20\"},{\"t\":\"bo\",\"v\":\"+5\",\"d\":1067}]}]},{\"n\":\"\uc5b4\ub824\uc6b4 \uc77c, \uc815\ub9d0 \uc88b\uc544\ud574\uc694!\",\"c\":[{\"o\":\"\u3088\u3057\u3001\u3084\u3063\u3066\u307f\u3088\u3046\uff01\",\"r\":[{\"t\":\"st\",\"v\":\"+5\"},{\"t\":\"gu\",\"v\":\"+10\"},{\"t\":\"bo\",\"v\":\"+5\",\"d\":1067}]},{\"o\":\"\u307e\u305a\u306f1\u5ea6\u69d8\u5b50\u3092\u898b\u3088\u3046\",\"r\":[{\"t\":\"sk\",\"v\":\"+1\",\"d\":200851},{\"t\":\"bo\",\"v\":\"+5\",\"d\":1067}]}]}],\"arrows\":[{\"n\":\"\uc544\uc774\uc62c\ub77c\uc774\ud2b8\uc758 \uc815\uc2e0\",\"c\":[{\"o\":\"\u9078\u629e\u80a2\u7121\u3057\",\"r\":[{\"t\":\"mo\",\"v\":\"+1\"},{\"t\":\"in\",\"v\":\"+20\"},{\"t\":\"bo\",\"v\":\"+15\",\"d\":1067},{\"t\":\"di\"},{\"t\":\"mo\",\"v\":\"+1\"},{\"t\":\"in\",\"v\":\"+5\"},{\"t\":\"bo\",\"v\":\"+5\",\"d\":1067}]}]},{\"n\":\"\uc2e4\ub9ac\ub9c8\ub098\uc774\ud2b8\uc758 \ubc14\ub2f7\uac00\",\"c\":[{\"o\":\"\u9078\u629e\u80a2\u7121\u3057\",\"r\":[{\"t\":\"en\",\"v\":\"+10\"},{\"t\":\"sp\",\"v\":\"+10\"},{\"t\":\"pt\",\"v\":\"+10\"},{\"t\":\"sk\",\"v\":\"+2\",\"d\":202662},{\"t\":\"bo\",\"v\":\"+5\",\"d\":1067}]}]},{\"n\":\"\uce7c\uc138\ub3c4\ub2c8\uac00 \ube5b\ub09c\ub2e4\",\"c\":[{\"o\":\"\u59a5\u5354\u3057\u306a\u3044\u5fc3\u304c\u97ff\u3044\u305f\u304b\u306a\uff1f\",\"r\":[{\"t\":\"in\",\"v\":\"+30\"},{\"t\":\"sk\",\"v\":\"+2\",\"d\":202151},{\"t\":\"bo\",\"v\":\"+5\",\"d\":1067}]},{\"o\":\"\u307f\u3093\u306a\u3001\u3044\u3044\u9854\u3092\u3057\u3066\u3044\u308b\u306a\",\"r\":[{\"t\":\"sp\",\"v\":\"+10\"},{\"t\":\"in\",\"v\":\"+10\"},{\"t\":\"pt\",\"v\":\"+10\"},{\"t\":\"sk\",\"v\":\"+2\",\"d\":202091},{\"t\":\"bo\",\"v\":\"+5\",\"d\":1067}]}]}]}", "zh_tw": "{\"random\":[{\"n\":\"\u6700\u559c\u6b61\u65b0\u6771\u897f\uff01\",\"c\":[{\"o\":\"\u30c6\u30a3\u30fc\u30ab\u30c3\u30d7\u3067\u98f2\u3080\u306e\u304b\uff1f\",\"r\":[{\"t\":\"gu\",\"v\":\"+10\"},{\"t\":\"bo\",\"v\":\"+5\",\"d\":1067}]},{\"o\":\"\u30e1\u30ed\u30f3\u30bd\u30fc\u30c0\u306f\u521d\u3081\u3066\uff1f\",\"r\":[{\"t\":\"en\",\"v\":\"-10\"},{\"t\":\"st\",\"v\":\"+20\"},{\"t\":\"bo\",\"v\":\"+5\",\"d\":1067}]}]},{\"n\":\"\u6700\u559c\u6b61\u56f0\u96e3\u7684\u4e8b\u60c5\uff01\",\"c\":[{\"o\":\"\u3088\u3057\u3001\u3084\u3063\u3066\u307f\u3088\u3046\uff01\",\"r\":[{\"t\":\"st\",\"v\":\"+5\"},{\"t\":\"gu\",\"v\":\"+10\"},{\"t\":\"bo\",\"v\":\"+5\",\"d\":1067}]},{\"o\":\"\u307e\u305a\u306f1\u5ea6\u69d8\u5b50\u3092\u898b\u3088\u3046\",\"r\":[{\"t\":\"sk\",\"v\":\"+1\",\"d\":200851},{\"t\":\"bo\",\"v\":\"+5\",\"d\":1067}]}]}],\"arrows\":[{\"n\":\"\u5807\u9752\u77f3\u7684\u7cbe\u795e\",\"c\":[{\"o\":\"\u9078\u629e\u80a2\u7121\u3057\",\"r\":[{\"t\":\"mo\",\"v\":\"+1\"},{\"t\":\"in\",\"v\":\"+20\"},{\"t\":\"bo\",\"v\":\"+15\",\"d\":1067},{\"t\":\"di\"},{\"t\":\"mo\",\"v\":\"+1\"},{\"t\":\"in\",\"v\":\"+5\"},{\"t\":\"bo\",\"v\":\"+5\",\"d\":1067}]}]},{\"n\":\"\u77fd\u7dda\u77f3\u7684\u6c34\u908a\",\"c\":[{\"o\":\"\u9078\u629e\u80a2\u7121\u3057\",\"r\":[{\"t\":\"en\",\"v\":\"+10\"},{\"t\":\"sp\",\"v\":\"+10\"},{\"t\":\"pt\",\"v\":\"+10\"},{\"t\":\"sk\",\"v\":\"+2\",\"d\":202662},{\"t\":\"bo\",\"v\":\"+5\",\"d\":1067}]}]},{\"n\":\"\u7389\u9ad3\u9583\u8000\",\"c\":[{\"o\":\"\u59a5\u5354\u3057\u306a\u3044\u5fc3\u304c\u97ff\u3044\u305f\u304b\u306a\uff1f\",\"r\":[{\"t\":\"in\",\"v\":\"+30\"},{\"t\":\"sk\",\"v\":\"+2\",\"d\":202151},{\"t\":\"bo\",\"v\":\"+5\",\"d\":1067}]},{\"o\":\"\u307f\u3093\u306a\u3001\u3044\u3044\u9854\u3092\u3057\u3066\u3044\u308b\u306a\",\"r\":[{\"t\":\"sp\",\"v\":\"+10\"},{\"t\":\"in\",\"v\":\"+10\"},{\"t\":\"pt\",\"v\":\"+10\"},{\"t\":\"sk\",\"v\":\"+2\",\"d\":202091},{\"t\":\"bo\",\"v\":\"+5\",\"d\":1067}]}]}]}", "en": "{\"random\":[{\"n\":\"\u65b0\u3057\u3044\u3082\u306e\u3001\u5927\u597d\u304d\u3067\u3059\uff01\",\"c\":[{\"o\":\"\u30c6\u30a3\u30fc\u30ab\u30c3\u30d7\u3067\u98f2\u3080\u306e\u304b\uff1f\",\"r\":[{\"t\":\"gu\",\"v\":\"+10\"},{\"t\":\"bo\",\"v\":\"+5\",\"d\":1067}]},{\"o\":\"\u30e1\u30ed\u30f3\u30bd\u30fc\u30c0\u306f\u521d\u3081\u3066\uff1f\",\"r\":[{\"t\":\"en\",\"v\":\"-10\"},{\"t\":\"st\",\"v\":\"+20\"},{\"t\":\"bo\",\"v\":\"+5\",\"d\":1067}]}]},{\"n\":\"\u96e3\u3057\u3044\u3053\u3068\u3001\u5927\u597d\u304d\u3067\u3059\uff01\",\"c\":[{\"o\":\"\u3088\u3057\u3001\u3084\u3063\u3066\u307f\u3088\u3046\uff01\",\"r\":[{\"t\":\"st\",\"v\":\"+5\"},{\"t\":\"gu\",\"v\":\"+10\"},{\"t\":\"bo\",\"v\":\"+5\",\"d\":1067}]},{\"o\":\"\u307e\u305a\u306f1\u5ea6\u69d8\u5b50\u3092\u898b\u3088\u3046\",\"r\":[{\"t\":\"sk\",\"v\":\"+1\",\"d\":200851},{\"t\":\"bo\",\"v\":\"+5\",\"d\":1067}]}]}],\"arrows\":[{\"n\":\"\u30a2\u30a4\u30aa\u30e9\u30a4\u30c8\u306e\u7cbe\u795e\",\"c\":[{\"o\":\"\u9078\u629e\u80a2\u7121\u3057\",\"r\":[{\"t\":\"mo\",\"v\":\"+1\"},{\"t\":\"in\",\"v\":\"+20\"},{\"t\":\"bo\",\"v\":\"+15\",\"d\":1067},{\"t\":\"di\"},{\"t\":\"mo\",\"v\":\"+1\"},{\"t\":\"in\",\"v\":\"+5\"},{\"t\":\"bo\",\"v\":\"+5\",\"d\":1067}]}]},{\"n\":\"\u30b7\u30ea\u30de\u30ca\u30a4\u30c8\u306e\u6e1a\",\"c\":[{\"o\":\"\u9078\u629e\u80a2\u7121\u3057\",\"r\":[{\"t\":\"en\",\"v\":\"+10\"},{\"t\":\"sp\",\"v\":\"+10\"},{\"t\":\"pt\",\"v\":\"+10\"},{\"t\":\"sk\",\"v\":\"+2\",\"d\":202662},{\"t\":\"bo\",\"v\":\"+5\",\"d\":1067}]}]},{\"n\":\"\u30ab\u30eb\u30bb\u30c9\u30cb\u30fc\u304c\u8f1d\u304f\",\"c\":[{\"o\":\"\u59a5\u5354\u3057\u306a\u3044\u5fc3\u304c\u97ff\u3044\u305f\u304b\u306a\uff1f\",\"r\":[{\"t\":\"in\",\"v\":\"+30\"},{\"t\":\"sk\",\"v\":\"+2\",\"d\":202151},{\"t\":\"bo\",\"v\":\"+5\",\"d\":1067}]},{\"o\":\"\u307f\u3093\u306a\u3001\u3044\u3044\u9854\u3092\u3057\u3066\u3044\u308b\u306a\",\"r\":[{\"t\":\"sp\",\"v\":\"+10\"},{\"t\":\"in\",\"v\":\"+10\"},{\"t\":\"pt\",\"v\":\"+10\"},{\"t\":\"sk\",\"v\":\"+2\",\"d\":202091},{\"t\":\"bo\",\"v\":\"+5\",\"d\":1067}]}]}]}"}, "profileUrlName": "satono-diamond", "isLevelDependand": false}